acore_spellscript_refactor/__init__.py
acore_spellscript_refactor/discover.py
acore_spellscript_refactor/main.py
acore_spellscript_refactor/refactor.py
acore_spellscript_refactor/util/__init__.py
acore_spellscript_refactor/util/colors.py
acore_spellscript_refactor/util/db.py
acore_spellscript_refactor/util/logger.py
acore_spellscript_refactor-1.8.4.dist-info/METADATA
acore_spellscript_refactor-1.8.4.dist-info/WHEEL
acore_spellscript_refactor-1.8.4.dist-info/RECORD
