Metadata-Version: 2.3
Name: acore_spellscript_refactor
Version: 1.8.4
Summary: tool that finds the first SpellScript by searching for public SpellScriptLoader in a file and converts it to use registry macros
Project-URL: Homepage, https://github.com/sogladev/spellscript-refactor-tool
Requires-Python: >=3.10
Requires-Dist: mysql-connector-python>=8.0.0
